mcpf_core/core/__init__.py
mcpf_core/core/arginjector.py
mcpf_core/core/constants.py
mcpf_core/core/decorators.py
mcpf_core/core/routines.py
mcpf_core/core/runtime.py
mcpf_core/core/singletons.py
mcpf_core/core/types.py
mcpf_core/func/__init__.py
mcpf_core/func/constants.py
mcpf_core/func/time.py
mcpf_core/run/__init__.py
mcpf_core/run/__main__.py
mcpf_core-0.1.0.dist-info/LICENSE
mcpf_core-0.1.0.dist-info/METADATA
mcpf_core-0.1.0.dist-info/WHEEL
mcpf_core-0.1.0.dist-info/RECORD
