Metadata-Version: 2.1
Name: mcpf-core
Version: 0.1.0
Summary: Minimalist Configurable Pipelineing Framework -- Core
License: MIT
Author: Karoly Bosa
Author-email: karoly.bosa@risc-software.at
Requires-Python: >=3.10,<4.0
Classifier: License :: OSI Approved :: MIT License
Classifier: Programming Language :: Python :: 3
Classifier: Programming Language :: Python :: 3.10
Classifier: Programming Language :: Python :: 3.11
Classifier: Programming Language :: Python :: 3.12
Requires-Dist: risc-lasagna (>=2.0.0,<3.0.0)
Requires-Dist: toolz (>=0.12.1,<0.13.0)
Project-URL: Example, https://www.risc-software.at/app/uploads/2025/05/mcpf-getting-started.zip
